<?xml version="1.0" encoding="UTF-8" standalone="no"?>
<pk><wd nm="your" rd="1,0:1147|2,0:1165|3,0:1167|9,0:147,510|16,0:689|23,0:1872|29,0:1337|42,0:585|49,0:2196|50,0:1479|54,0:126,489|64,0:1631,1760|66,0:67,479|71,0:121|85,0:149,512|103,0:592|104,0:620|105,0:620|115,0:149,512|126,0:204|130,0:236|137,0:1679|147,0:1807|149,0:948|150,0:1458,1503|152,0:1464,1509|157,0:124,487|163,0:994,1105|171,0:1202|173,0:882|190,0:161|205,0:149,512|210,0:1625|224,0:1412|232,0:591|242,0:178,469|244,0:151,514"/><wd nm="yyyy" rd="40,0:1636|206,0:563,583"/><wd nm="z" rd="50,0:1033,1037"/><wd nm="zon" rd="42,0:425,469,505,596|93,0:1435,1463|224,0:1493,1532,1558,1643"/><wd nm="zone" rd="42,0:548"/><wd nm="zoom" rd="56,0:2931,2940"/><wd nm="{" rd="56,0:4901"/><wd nm="}" rd="56,0:4913"/><wd nm="–" rd="21,0:534,537|23,0:553,556|26,0:429,432|74,0:1863|101,0:303,306|137,0:1274,1277|197,0:1081|206,0:587,1363|208,0:1131|217,0:896|218,0:1915|247,0:592,595"/><wd nm="“" rd="21,0:922|26,0:857|56,0:2193,4835|132,0:728|167,0:474"/><wd nm="”" rd="21,0:930|26,0:864|56,0:2197,4840|132,0:739|167,0:483"/><wd nm="•" rd="243,0:978,996,1008|245,0:1051,1078,1098"/></pk>